[
  {
    "model": "auth.user",
    "pk": 1,
    "fields": {
      "password": "pbkdf2_sha256$260000$FQ50K49aOkQnzZWhjW1Uxb$QeMvKAQwkw5mBsgjtEilSC6E3TdxbWbdCEhSs0JlSq8=",
      "last_login": "2022-02-11T10:48:23.437Z",
      "is_superuser": true,
      "username": "serveradmin",
      "first_name": "",
      "last_name": "",
      "email": "",
      "is_staff": true,
      "is_active": true,
      "date_joined": "2022-02-11T10:47:40.821Z",
      "groups": [],
      "user_permissions": []
    }
  }
]
